setup.py
shopify_trois/__init__.py
shopify_trois/collection.py
shopify_trois/credentials.py
shopify_trois/exceptions.py
shopify_trois.egg-info/PKG-INFO
shopify_trois.egg-info/SOURCES.txt
shopify_trois.egg-info/dependency_links.txt
shopify_trois.egg-info/not-zip-safe
shopify_trois.egg-info/requires.txt
shopify_trois.egg-info/top_level.txt
shopify_trois/engines/__init__.py
shopify_trois/engines/http/__init__.py
shopify_trois/engines/http/json.py
shopify_trois/engines/http/oauth_engine.py
shopify_trois/engines/http/request.py
shopify_trois/models/__init__.py
shopify_trois/models/application_charge.py
shopify_trois/models/article.py
shopify_trois/models/asset.py
shopify_trois/models/blog.py
shopify_trois/models/carrier_service.py
shopify_trois/models/checkout.py
shopify_trois/models/collect.py
shopify_trois/models/comment.py
shopify_trois/models/country.py
shopify_trois/models/custom_collection.py
shopify_trois/models/customer.py
shopify_trois/models/customer_group.py
shopify_trois/models/event.py
shopify_trois/models/fulfillment.py
shopify_trois/models/fulfillment_service.py
shopify_trois/models/metafield.py
shopify_trois/models/model.py
shopify_trois/models/order.py
shopify_trois/models/order_risk.py
shopify_trois/models/page.py
shopify_trois/models/product.py
shopify_trois/models/product_image.py
shopify_trois/models/product_search_engine.py
shopify_trois/models/product_variant.py
shopify_trois/models/province.py
shopify_trois/models/recurring_application_charge.py
shopify_trois/models/redirect.py
shopify_trois/models/script_tag.py
shopify_trois/models/shop.py
shopify_trois/models/smart_collection.py
shopify_trois/models/theme.py
shopify_trois/models/transaction.py
shopify_trois/models/webhook.py